README.md
pyproject.toml
setup.cfg
setup.py
cffi_src/__init__.py
cffi_src/openssl_build.py
symbol_lightapi.egg-info/PKG-INFO
symbol_lightapi.egg-info/SOURCES.txt
symbol_lightapi.egg-info/dependency_links.txt
symbol_lightapi.egg-info/not-zip-safe
symbol_lightapi.egg-info/top_level.txt
symbollightapi/__init__.py
symbollightapi/bindings/__init__.py
symbollightapi/bindings/openssl.py
symbollightapi/connector/BasicConnector.py
symbollightapi/connector/CatapultCertificateProcessor.py
symbollightapi/connector/CertificateUtils.py
symbollightapi/connector/NemConnector.py
symbollightapi/connector/SymbolConnector.py
symbollightapi/connector/SymbolPeerConnector.py
symbollightapi/connector/__init__.py
symbollightapi/model/Endpoint.py
symbollightapi/model/Exceptions.py
symbollightapi/model/NodeInfo.py
symbollightapi/model/PacketHeader.py
symbollightapi/model/__init__.py
tests/__init__.py
tests/connector/__init__.py
tests/connector/test_BasicConnector.py
tests/connector/test_CatapultCertificateProcessor.py
tests/connector/test_CertificateUtils.py
tests/connector/test_NemConnector.py
tests/connector/test_SymbolConnector.py
tests/connector/test_SymbolPeerConnector.py
tests/model/__init__.py
tests/model/test_Endpoint.py
tests/model/test_NodeInfo.py
tests/model/test_PacketHeader.py
tests/test/CertificateTestUtils.py
tests/test/__init__.py