Metadata-Version: 2.1
Name: symbol-lightapi
Version: 0.0.3
Summary: Symbol Light API
Home-page: https://github.com/symbol/product/tree/main/python/lightapi
Author: Symbol Contributors
Author-email: contributors@symbol.dev
License: MIT
Keywords: symbol,symbollightapi,lightapi,Symbol Light API
Classifier: Programming Language :: Python :: 3.7
Requires-Python: >=3.7
